{"elapsedTime":"0.14 secs","count":33,"data":[{"typeCode":"C","freqCode":"A","refPeriodId":20230101,"refYear":2023,"refMonth":52,"period":"2023","reporterCode":156,"reporterISO":"CHN","reporterDesc":"China","flowCode":"M","flowDesc":"Import","partnerCode":0,"partnerISO":"W00","partnerDesc":"World","partner2Code":0,"partner2ISO":"W00","partner2Desc":"World","classificationCode":"H6","classificationSearchCode":"HS","isOriginalClassification":true,"cmdCode":"2846","cmdDesc":"Compounds, inorganic or organic, of rare-earth metals; of yttrium or of scandium or of mixtures of these metals","aggrLevel":4,"isLeaf":false,"customsCode":"C00","customsDesc":"TOTAL CPC","mosCode":"0","motCode":0,"motDesc":"TOTAL MOT","qtyUnitCode":8,"qtyUnitAbbr":"kg","qty":109285772.57,"isQtyEstimated":true,"altQtyUnitCode":-1,"altQtyUnitAbbr":"N/A","altQty":0.0,"isAltQtyEstimated":false,"netWgt":109285772.57,"isNetWgtEstimated":true,"grossWgt":0.0,"isGrossWgtEstimated":false,"cifvalue":1881334377.0,"fobvalue":null,"primaryValue":1881334377.0,"legacyEstimationFlag":6,"isReported":false,"isAggregate":true},{"typeCode":"C","freqCode":"A","refPeriodId":20230101,"refYear":2023,"refMonth":52,"period":"2023","reporterCode":156,"reporterISO":"CHN","reporterDesc":"China","flowCode":"M","flowDesc":"Import","partnerCode":40,"partnerISO":"AUT","partnerDesc":"Austria","partner2Code":0,"partner2ISO":"W00","partner2Desc":"World","classificationCode":"H6","classificationSearchCode":"HS","isOriginalClassification":true,"cmdCode":"2846","cmdDesc":"Compounds, inorganic or organic, of rare-earth metals; of yttrium or of scandium or of mixtures of these metals","aggrLevel":4,"isLeaf":false,"customsCode":"C00","customsDesc":"TOTAL CPC","mosCode":"0","motCode":0,"motDesc":"TOTAL MOT","qtyUnitCode":8,"qtyUnitAbbr":"kg","qty":2618.57,"isQtyEstimated":true,"altQtyUnitCode":-1,"altQtyUnitAbbr":"N/A","altQty":0.0,"isAltQtyEstimated":false,"netWgt":2618.57,"isNetWgtEstimated":true,"grossWgt":0.0,"isGrossWgtEstimated":false,"cifvalue":77694.0,"fobvalue":null,"primaryValue":77694.0,"legacyEstimationFlag":6,"isReported":false,"isAggregate":true},{"typeCode":"C","freqCode":"A","refPeriodId":20230101,"refYear":2023,"refMonth":52,"period":"2023","reporterCode":156,"reporterISO":"CHN","reporterDesc":"China","flowCode":"M","flowDesc":"Import","partnerCode":104,"partnerISO":"MMR","partnerDesc":"Myanmar","partner2Code":0,"partner2ISO":"W00","partner2Desc":"World","classificationCode":"H6","classificationSearchCode":"HS","isOriginalClassification":true,"cmdCode":"2846","cmdDesc":"Compounds, inorganic or organic, of rare-earth metals; of yttrium or of scandium or of mixtures of these metals","aggrLevel":4,"isLeaf":false,"customsCode":"C00","customsDesc":"TOTAL CPC","mosCode":"0","motCode":0,"motDesc":"TOTAL MOT","qtyUnitCode":8,"qtyUnitAbbr":"kg","qty":72073760.0,"isQtyEstimated":false,"altQtyUnitCode":8,"altQtyUnitAbbr":"kg","altQty":72073760.0,"isAltQtyEstimated":false,"netWgt":72073760.0,"isNetWgtEstimated":false,"grossWgt":0.0,"isGrossWgtEstimated":false,"cifvalue":1441901598.0,"fobvalue":null,"primaryValue":1441901598.0,"legacyEstimationFlag":0,"isReported":false,"isAggregate":true},{"typeCode":"C","freqCode":"A","refPeriodId":20230101,"refYear":2023,"refMonth":52,"period":"2023","reporterCode":156,"reporterISO":"CHN","reporterDesc":"China","flowCode":"M","flowDesc":"Import","partnerCode":124,"partnerISO":"CAN","partnerDesc":"Canada","partner2Code":0,"partner2ISO":"W00","partner2Desc":"World","classificationCode":"H6","classificationSearchCode":"HS","isOriginalClassification":true,"cmdCode":"2846","cmdDesc":"Compounds, inorganic or organic, of rare-earth metals; of yttrium or of scandium or of mixtures of these metals","aggrLevel":4,"isLeaf":false,"customsCode":"C00","customsDesc":"TOTAL CPC","mosCode":"0","motCode":0,"motDesc":"TOTAL MOT","qtyUnitCode":8,"qtyUnitAbbr":"kg","qty":520.316,"isQtyEstimated":true,"altQtyUnitCode":-1,"altQtyUnitAbbr":"N/A","altQty":0.0,"isAltQtyEstimated":false,"netWgt":520.316,"isNetWgtEstimated":true,"grossWgt":0.0,"isGrossWgtEstimated":false,"cifvalue":9160.0,"fobvalue":null,"primaryValue":9160.0,"legacyEstimationFlag":6,"isReported":false,"isAggregate":true},{"typeCode":"C","freqCode":"A","refPeriodId":20230101,"refYear":2023,"refMonth":52,"period":"2023","reporterCode":156,"reporterISO":"CHN","reporterDesc":"China","flowCode":"M","flowDesc":"Import","partnerCode":156,"partnerISO":"CHN","partnerDesc":"China","partner2Code":0,"partner2ISO":"W00","partner2Desc":"World","classificationCode":"H6","classificationSearchCode":"HS","isOriginalClassification":true,"cmdCode":"2846","cmdDesc":"Compounds, inorganic or organic, of rare-earth metals; of yttrium or of scandium or of mixtures of these metals","aggrLevel":4,"isLeaf":false,"customsCode":"C00","customsDesc":"TOTAL CPC","mosCode":"0","motCode":0,"motDesc":"TOTAL MOT","qtyUnitCode":8,"qtyUnitAbbr":"kg","qty":117496.267,"isQtyEstimated":true,"altQtyUnitCode":-1,"altQtyUnitAbbr":"N/A","altQty":0.0,"isAltQtyEstimated":false,"netWgt":117496.267,"isNetWgtEstimated":true,"grossWgt":0.0,"isGrossWgtEstimated":false,"cifvalue":1963701.0,"fobvalue":null,"primaryValue":1963701.0,"legacyEstimationFlag":6,"isReported":false,"isAggregate":true},{"typeCode":"C","freqCode":"A","refPeriodId":20230101,"refYear":2023,"refMonth":52,"period":"2023","reporterCode":156,"reporterISO":"CHN","reporterDesc":"China","flowCode":"M","flowDesc":"Import","partnerCode":203,"partnerISO":"CZE","partnerDesc":"Czechia","partner2Code":0,"partner2ISO":"W00","partner2Desc":"World","classificationCode":"H6","classificationSearchCode":"HS","isOriginalClassification":true,"cmdCode":"2846","cmdDesc":"Compounds, inorganic or organic, of rare-earth metals; of yttrium or of scandium or of mixtures of these metals","aggrLevel":4,"isLeaf":false,"customsCode":"C00","customsDesc":"TOTAL CPC","mosCode":"0","motCode":0,"motDesc":"TOTAL MOT","qtyUnitCode":8,"qtyUnitAbbr":"kg","qty":1.306,"isQtyEstimated":true,"altQtyUnitCode":-1,"altQtyUnitAbbr":"N/A","altQty":0.0,"isAltQtyEstimated":false,"netWgt":1.306,"isNetWgtEstimated":true,"grossWgt":0.0,"isGrossWgtEstimated":false,"cifvalue":23.0,"fobvalue":null,"primaryValue":23.0,"legacyEstimationFlag":6,"isReported":false,"isAggregate":true},{"typeCode":"C","freqCode":"A","refPeriodId":20230101,"refYear":2023,"refMonth":52,"period":"2023","reporterCode":156,"reporterISO":"CHN","reporterDesc":"China","flowCode":"M","flowDesc":"Import","partnerCode":233,"partnerISO":"EST","partnerDesc":"Estonia","partner2Code":0,"partner2ISO":"W00","partner2Desc":"World","classificationCode":"H6","classificationSearchCode":"HS","isOriginalClassification":true,"cmdCode":"2846","cmdDesc":"Compounds, inorganic or organic, of rare-earth metals; of yttrium or of scandium or of mixtures of these metals","aggrLevel":4,"isLeaf":false,"customsCode":"C00","customsDesc":"TOTAL CPC","mosCode":"0","motCode":0,"motDesc":"TOTAL MOT","qtyUnitCode":8,"qtyUnitAbbr":"kg","qty":110000.0,"isQtyEstimated":false,"altQtyUnitCode":8,"altQtyUnitAbbr":"kg","altQty":110000.0,"isAltQtyEstimated":false,"netWgt":110000.0,"isNetWgtEstimated":false,"grossWgt":0.0,"isGrossWgtEstimated":false,"cifvalue":4100500.0,"fobvalue":null,"primaryValue":4100500.0,"legacyEstimationFlag":0,"isReported":false,"isAggregate":true},{"typeCode":"C","freqCode":"A","refPeriodId":20230101,"refYear":2023,"refMonth":52,"period":"2023","reporterCode":156,"reporterISO":"CHN","reporterDesc":"China","flowCode":"M","flowDesc":"Import","partnerCode":246,"partnerISO":"FIN","partnerDesc":"Finland","partner2Code":0,"partner2ISO":"W00","partner2Desc":"World","classificationCode":"H6","classificationSearchCode":"HS","isOriginalClassification":true,"cmdCode":"2846","cmdDesc":"Compounds, inorganic or organic, of rare-earth metals; of yttrium or of scandium or of mixtures of these metals","aggrLevel":4,"isLeaf":false,"customsCode":"C00","customsDesc":"TOTAL CPC","mosCode":"0","motCode":0,"motDesc":"TOTAL MOT","qtyUnitCode":8,"qtyUnitAbbr":"kg","qty":172.681,"isQtyEstimated":true,"altQtyUnitCode":-1,"altQtyUnitAbbr":"N/A","altQty":0.0,"isAltQtyEstimated":false,"netWgt":172.681,"isNetWgtEstimated":true,"grossWgt":0.0,"isGrossWgtEstimated":false,"cifvalue":3040.0,"fobvalue":null,"primaryValue":3040.0,"legacyEstimationFlag":6,"isReported":false,"isAggregate":true},{"typeCode":"C","freqCode":"A","refPeriodId":20230101,"refYear":2023,"refMonth":52,"period":"2023","reporterCode":156,"reporterISO":"CHN","reporterDesc":"China","flowCode":"M","flowDesc":"Import","partnerCode":251,"partnerISO":"FRA","partnerDesc":"France","partner2Code":0,"partner2ISO":"W00","partner2Desc":"World","classificationCode":"H6","classificationSearchCode":"HS","isOriginalClassification":true,"cmdCode":"2846","cmdDesc":"Compounds, inorganic or organic, of rare-earth metals; of yttrium or of scandium or of mixtures of these metals","aggrLevel":4,"isLeaf":false,"customsCode":"C00","customsDesc":"TOTAL CPC","mosCode":"0","motCode":0,"motDesc":"TOTAL MOT","qtyUnitCode":8,"qtyUnitAbbr":"kg","qty":13716.635,"isQtyEstimated":true,"altQtyUnitCode":-1,"altQtyUnitAbbr":"N/A","altQty":0.0,"isAltQtyEstimated":false,"netWgt":13716.635,"isNetWgtEstimated":true,"grossWgt":0.0,"isGrossWgtEstimated":false,"cifvalue":1364810.0,"fobvalue":null,"primaryValue":1364810.0,"legacyEstimationFlag":6,"isReported":false,"isAggregate":true},{"typeCode":"C","freqCode":"A","refPeriodId":20230101,"refYear":2023,"refMonth":52,"period":"2023","reporterCode":156,"reporterISO":"CHN","reporterDesc":"China","flowCode":"M","flowDesc":"Import","partnerCode":276,"partnerISO":"DEU","partnerDesc":"Germany","partner2Code":0,"partner2ISO":"W00","partner2Desc":"World","classificationCode":"H6","classificationSearchCode":"HS","isOriginalClassification":true,"cmdCode":"2846","cmdDesc":"Compounds, inorganic or organic, of rare-earth metals; of yttrium or of scandium or of mixtures of these metals","aggrLevel":4,"isLeaf":false,"customsCode":"C00","customsDesc":"TOTAL CPC","mosCode":"0","motCode":0,"motDesc":"TOTAL MOT","qtyUnitCode":8,"qtyUnitAbbr":"kg","qty":6150.196,"isQtyEstimated":true,"altQtyUnitCode":-1,"altQtyUnitAbbr":"N/A","altQty":0.0,"isAltQtyEstimated":false,"netWgt":6150.196,"isNetWgtEstimated":true,"grossWgt":0.0,"isGrossWgtEstimated":false,"cifvalue":2684985.0,"fobvalue":null,"primaryValue":2684985.0,"legacyEstimationFlag":6,"isReported":false,"isAggregate":true},{"typeCode":"C","freqCode":"A","refPeriodId":20230101,"refYear":2023,"refMonth":52,"period":"2023","reporterCode":156,"reporterISO":"CHN","reporterDesc":"China","flowCode":"M","flowDesc":"Import","partnerCode":372,"partnerISO":"IRL","partnerDesc":"Ireland","partner2Code":0,"partner2ISO":"W00","partner2Desc":"World","classificationCode":"H6","classificationSearchCode":"HS","isOriginalClassification":true,"cmdCode":"2846","cmdDesc":"Compounds, inorganic or organic, of rare-earth metals; of yttrium or of scandium or of mixtures of these metals","aggrLevel":4,"isLeaf":false,"customsCode":"C00","customsDesc":"TOTAL CPC","mosCode":"0","motCode":0,"motDesc":"TOTAL MOT","qtyUnitCode":8,"qtyUnitAbbr":"kg","qty":1.0,"isQtyEstimated":false,"altQtyUnitCode":8,"altQtyUnitAbbr":"kg","altQty":1.0,"isAltQtyEstimated":false,"netWgt":1.0,"isNetWgtEstimated":false,"grossWgt":0.0,"isGrossWgtEstimated":false,"cifvalue":1841.0,"fobvalue":null,"primaryValue":1841.0,"legacyEstimationFlag":0,"isReported":false,"isAggregate":true},{"typeCode":"C","freqCode":"A","refPeriodId":20230101,"refYear":2023,"refMonth":52,"period":"2023","reporterCode":156,"reporterISO":"CHN","reporterDesc":"China","flowCode":"M","flowDesc":"Import","partnerCode":380,"partnerISO":"ITA","partnerDesc":"Italy","partner2Code":0,"partner2ISO":"W00","partner2Desc":"World","classificationCode":"H6","classificationSearchCode":"HS","isOriginalClassification":true,"cmdCode":"2846","cmdDesc":"Compounds, inorganic or organic, of rare-earth metals; of yttrium or of scandium or of mixtures of these metals","aggrLevel":4,"isLeaf":false,"customsCode":"C00","customsDesc":"TOTAL CPC","mosCode":"0","motCode":0,"motDesc":"TOTAL MOT","qtyUnitCode":8,"qtyUnitAbbr":"kg","qty":1617.459,"isQtyEstimated":true,"altQtyUnitCode":-1,"altQtyUnitAbbr":"N/A","altQty":0.0,"isAltQtyEstimated":false,"netWgt":1617.459,"isNetWgtEstimated":true,"grossWgt":0.0,"isGrossWgtEstimated":false,"cifvalue":69321.0,"fobvalue":null,"primaryValue":69321.0,"legacyEstimationFlag":6,"isReported":false,"isAggregate":true},{"typeCode":"C","freqCode":"A","refPeriodId":20230101,"refYear":2023,"refMonth":52,"period":"2023","reporterCode":156,"reporterISO":"CHN","reporterDesc":"China","flowCode":"M","flowDesc":"Import","partnerCode":392,"partnerISO":"JPN","partnerDesc":"Japan","partner2Code":0,"partner2ISO":"W00","partner2Desc":"World","classificationCode":"H6","classificationSearchCode":"HS","isOriginalClassification":true,"cmdCode":"2846","cmdDesc":"Compounds, inorganic or organic, of rare-earth metals; of yttrium or of scandium or of mixtures of these metals","aggrLevel":4,"isLeaf":false,"customsCode":"C00","customsDesc":"TOTAL CPC","mosCode":"0","motCode":0,"motDesc":"TOTAL MOT","qtyUnitCode":8,"qtyUnitAbbr":"kg","qty":435865.992,"isQtyEstimated":true,"altQtyUnitCode":-1,"altQtyUnitAbbr":"N/A","altQty":0.0,"isAltQtyEstimated":false,"netWgt":435865.992,"isNetWgtEstimated":true,"grossWgt":0.0,"isGrossWgtEstimated":false,"cifvalue":33039038.0,"fobvalue":null,"primaryValue":33039038.0,"legacyEstimationFlag":6,"isReported":false,"isAggregate":true},{"typeCode":"C","freqCode":"A","refPeriodId":20230101,"refYear":2023,"refMonth":52,"period":"2023","reporterCode":156,"reporterISO":"CHN","reporterDesc":"China","flowCode":"M","flowDesc":"Import","partnerCode":398,"partnerISO":"KAZ","partnerDesc":"Kazakhstan","partner2Code":0,"partner2ISO":"W00","partner2Desc":"World","classificationCode":"H6","classificationSearchCode":"HS","isOriginalClassification":true,"cmdCode":"2846","cmdDesc":"Compounds, inorganic or organic, of rare-earth metals; of yttrium or of scandium or of mixtures of these metals","aggrLevel":4,"isLeaf":false,"customsCode":"C00","customsDesc":"TOTAL CPC","mosCode":"0","motCode":0,"motDesc":"TOTAL MOT","qtyUnitCode":8,"qtyUnitAbbr":"kg","qty":1255554.0,"isQtyEstimated":false,"altQtyUnitCode":8,"altQtyUnitAbbr":"kg","altQty":1255554.0,"isAltQtyEstimated":false,"netWgt":1255554.0,"isNetWgtEstimated":false,"grossWgt":0.0,"isGrossWgtEstimated":false,"cifvalue":9029723.0,"fobvalue":null,"primaryValue":9029723.0,"legacyEstimationFlag":0,"isReported":false,"isAggregate":true},{"typeCode":"C","freqCode":"A","refPeriodId":20230101,"refYear":2023,"refMonth":52,"period":"2023","reporterCode":156,"reporterISO":"CHN","reporterDesc":"China","flowCode":"M","flowDesc":"Import","partnerCode":410,"partnerISO":"KOR","partnerDesc":"Rep. of Korea","partner2Code":0,"partner2ISO":"W00","partner2Desc":"World","classificationCode":"H6","classificationSearchCode":"HS","isOriginalClassification":true,"cmdCode":"2846","cmdDesc":"Compounds, inorganic or organic, of rare-earth metals; of yttrium or of scandium or of mixtures of these metals","aggrLevel":4,"isLeaf":false,"customsCode":"C00","customsDesc":"TOTAL CPC","mosCode":"0","motCode":0,"motDesc":"TOTAL MOT","qtyUnitCode":8,"qtyUnitAbbr":"kg","qty":32654.0,"isQtyEstimated":false,"altQtyUnitCode":8,"altQtyUnitAbbr":"kg","altQty":32654.0,"isAltQtyEstimated":false,"netWgt":32654.0,"isNetWgtEstimated":false,"grossWgt":0.0,"isGrossWgtEstimated":false,"cifvalue":4593861.0,"fobvalue":null,"primaryValue":4593861.0,"legacyEstimationFlag":0,"isReported":false,"isAggregate":true},{"typeCode":"C","freqCode":"A","refPeriodId":20230101,"refYear":2023,"refMonth":52,"period":"2023","reporterCode":156,"reporterISO":"CHN","reporterDesc":"China","flowCode":"M","flowDesc":"Import","partnerCode":418,"partnerISO":"LAO","partnerDesc":"Lao People's Dem. Rep.","partner2Code":0,"partner2ISO":"W00","partner2Desc":"World","classificationCode":"H6","classificationSearchCode":"HS","isOriginalClassification":true,"cmdCode":"2846","cmdDesc":"Compounds, inorganic or organic, of rare-earth metals; of yttrium or of scandium or of mixtures of these metals","aggrLevel":4,"isLeaf":false,"customsCode":"C00","customsDesc":"TOTAL CPC","mosCode":"0","motCode":0,"motDesc":"TOTAL MOT","qtyUnitCode":8,"qtyUnitAbbr":"kg","qty":11307691.0,"isQtyEstimated":false,"altQtyUnitCode":8,"altQtyUnitAbbr":"kg","altQty":11307691.0,"isAltQtyEstimated":false,"netWgt":11307691.0,"isNetWgtEstimated":false,"grossWgt":0.0,"isGrossWgtEstimated":false,"cifvalue":103657219.0,"fobvalue":null,"primaryValue":103657219.0,"legacyEstimationFlag":0,"isReported":false,"isAggregate":true},{"typeCode":"C","freqCode":"A","refPeriodId":20230101,"refYear":2023,"refMonth":52,"period":"2023","reporterCode":156,"reporterISO":"CHN","reporterDesc":"China","flowCode":"M","flowDesc":"Import","partnerCode":458,"partnerISO":"MYS","partnerDesc":"Malaysia","partner2Code":0,"partner2ISO":"W00","partner2Desc":"World","classificationCode":"H6","classificationSearchCode":"HS","isOriginalClassification":true,"cmdCode":"2846","cmdDesc":"Compounds, inorganic or organic, of rare-earth metals; of yttrium or of scandium or of mixtures of these metals","aggrLevel":4,"isLeaf":false,"customsCode":"C00","customsDesc":"TOTAL CPC","mosCode":"0","motCode":0,"motDesc":"TOTAL MOT","qtyUnitCode":8,"qtyUnitAbbr":"kg","qty":19084528.174,"isQtyEstimated":true,"altQtyUnitCode":-1,"altQtyUnitAbbr":"N/A","altQty":0.0,"isAltQtyEstimated":false,"netWgt":19084528.174,"isNetWgtEstimated":true,"grossWgt":0.0,"isGrossWgtEstimated":false,"cifvalue":214676059.0,"fobvalue":null,"primaryValue":214676059.0,"legacyEstimationFlag":6,"isReported":false,"isAggregate":true},{"typeCode":"C","freqCode":"A","refPeriodId":20230101,"refYear":2023,"refMonth":52,"period":"2023","reporterCode":156,"reporterISO":"CHN","reporterDesc":"China","flowCode":"M","flowDesc":"Import","partnerCode":484,"partnerISO":"MEX","partnerDesc":"Mexico","partner2Code":0,"partner2ISO":"W00","partner2Desc":"World","classificationCode":"H6","classificationSearchCode":"HS","isOriginalClassification":true,"cmdCode":"2846","cmdDesc":"Compounds, inorganic or organic, of rare-earth metals; of yttrium or of scandium or of mixtures of these metals","aggrLevel":4,"isLeaf":false,"customsCode":"C00","customsDesc":"TOTAL CPC","mosCode":"0","motCode":0,"motDesc":"TOTAL MOT","qtyUnitCode":8,"qtyUnitAbbr":"kg","qty":11.077,"isQtyEstimated":true,"altQtyUnitCode":-1,"altQtyUnitAbbr":"N/A","altQty":0.0,"isAltQtyEstimated":false,"netWgt":11.077,"isNetWgtEstimated":true,"grossWgt":0.0,"isGrossWgtEstimated":false,"cifvalue":195.0,"fobvalue":null,"primaryValue":195.0,"legacyEstimationFlag":6,"isReported":false,"isAggregate":true},{"typeCode":"C","freqCode":"A","refPeriodId":20230101,"refYear":2023,"refMonth":52,"period":"2023","reporterCode":156,"reporterISO":"CHN","reporterDesc":"China","flowCode":"M","flowDesc":"Import","partnerCode":490,"partnerISO":"S19","partnerDesc":"Other Asia, nes","partner2Code":0,"partner2ISO":"W00","partner2Desc":"World","classificationCode":"H6","classificationSearchCode":"HS","isOriginalClassification":true,"cmdCode":"2846","cmdDesc":"Compounds, inorganic or organic, of rare-earth metals; of yttrium or of scandium or of mixtures of these metals","aggrLevel":4,"isLeaf":false,"customsCode":"C00","customsDesc":"TOTAL CPC","mosCode":"0","motCode":0,"motDesc":"TOTAL MOT","qtyUnitCode":8,"qtyUnitAbbr":"kg","qty":1142.101,"isQtyEstimated":true,"altQtyUnitCode":-1,"altQtyUnitAbbr":"N/A","altQty":0.0,"isAltQtyEstimated":false,"netWgt":1142.101,"isNetWgtEstimated":true,"grossWgt":0.0,"isGrossWgtEstimated":false,"cifvalue":1423794.0,"fobvalue":null,"primaryValue":1423794.0,"legacyEstimationFlag":6,"isReported":false,"isAggregate":true},{"typeCode":"C","freqCode":"A","refPeriodId":20230101,"refYear":2023,"refMonth":52,"period":"2023","reporterCode":156,"reporterISO":"CHN","reporterDesc":"China","flowCode":"M","flowDesc":"Import","partnerCode":579,"partnerISO":"NOR","partnerDesc":"Norway","partner2Code":0,"partner2ISO":"W00","partner2Desc":"World","classificationCode":"H6","classificationSearchCode":"HS","isOriginalClassification":true,"cmdCode":"2846","cmdDesc":"Compounds, inorganic or organic, of rare-earth metals; of yttrium or of scandium or of mixtures of these metals","aggrLevel":4,"isLeaf":false,"customsCode":"C00","customsDesc":"TOTAL CPC","mosCode":"0","motCode":0,"motDesc":"TOTAL MOT","qtyUnitCode":8,"qtyUnitAbbr":"kg","qty":4.363,"isQtyEstimated":true,"altQtyUnitCode":-1,"altQtyUnitAbbr":"N/A","altQty":0.0,"isAltQtyEstimated":false,"netWgt":4.363,"isNetWgtEstimated":true,"grossWgt":0.0,"isGrossWgtEstimated":false,"cifvalue":3489.0,"fobvalue":null,"primaryValue":3489.0,"legacyEstimationFlag":6,"isReported":false,"isAggregate":true},{"typeCode":"C","freqCode":"A","refPeriodId":20230101,"refYear":2023,"refMonth":52,"period":"2023","reporterCode":156,"reporterISO":"CHN","reporterDesc":"China","flowCode":"M","flowDesc":"Import","partnerCode":620,"partnerISO":"PRT","partnerDesc":"Portugal","partner2Code":0,"partner2ISO":"W00","partner2Desc":"World","classificationCode":"H6","classificationSearchCode":"HS","isOriginalClassification":true,"cmdCode":"2846","cmdDesc":"Compounds, inorganic or organic, of rare-earth metals; of yttrium or of scandium or of mixtures of these metals","aggrLevel":4,"isLeaf":false,"customsCode":"C00","customsDesc":"TOTAL CPC","mosCode":"0","motCode":0,"motDesc":"TOTAL MOT","qtyUnitCode":8,"qtyUnitAbbr":"kg","qty":152.0,"isQtyEstimated":false,"altQtyUnitCode":8,"altQtyUnitAbbr":"kg","altQty":152.0,"isAltQtyEstimated":false,"netWgt":152.0,"isNetWgtEstimated":false,"grossWgt":0.0,"isGrossWgtEstimated":false,"cifvalue":13986.0,"fobvalue":null,"primaryValue":13986.0,"legacyEstimationFlag":0,"isReported":false,"isAggregate":true},{"typeCode":"C","freqCode":"A","refPeriodId":20230101,"refYear":2023,"refMonth":52,"period":"2023","reporterCode":156,"reporterISO":"CHN","reporterDesc":"China","flowCode":"M","flowDesc":"Import","partnerCode":643,"partnerISO":"RUS","partnerDesc":"Russian Federation","partner2Code":0,"partner2ISO":"W00","partner2Desc":"World","classificationCode":"H6","classificationSearchCode":"HS","isOriginalClassification":true,"cmdCode":"2846","cmdDesc":"Compounds, inorganic or organic, of rare-earth metals; of yttrium or of scandium or of mixtures of these metals","aggrLevel":4,"isLeaf":false,"customsCode":"C00","customsDesc":"TOTAL CPC","mosCode":"0","motCode":0,"motDesc":"TOTAL MOT","qtyUnitCode":8,"qtyUnitAbbr":"kg","qty":242701.078,"isQtyEstimated":true,"altQtyUnitCode":-1,"altQtyUnitAbbr":"N/A","altQty":0.0,"isAltQtyEstimated":false,"netWgt":242701.078,"isNetWgtEstimated":true,"grossWgt":0.0,"isGrossWgtEstimated":false,"cifvalue":1001323.0,"fobvalue":null,"primaryValue":1001323.0,"legacyEstimationFlag":6,"isReported":false,"isAggregate":true},{"typeCode":"C","freqCode":"A","refPeriodId":20230101,"refYear":2023,"refMonth":52,"period":"2023","reporterCode":156,"reporterISO":"CHN","reporterDesc":"China","flowCode":"M","flowDesc":"Import","partnerCode":699,"partnerISO":"IND","partnerDesc":"India","partner2Code":0,"partner2ISO":"W00","partner2Desc":"World","classificationCode":"H6","classificationSearchCode":"HS","isOriginalClassification":true,"cmdCode":"2846","cmdDesc":"Compounds, inorganic or organic, of rare-earth metals; of yttrium or of scandium or of mixtures of these metals","aggrLevel":4,"isLeaf":false,"customsCode":"C00","customsDesc":"TOTAL CPC","mosCode":"0","motCode":0,"motDesc":"TOTAL MOT","qtyUnitCode":8,"qtyUnitAbbr":"kg","qty":805860.172,"isQtyEstimated":true,"altQtyUnitCode":-1,"altQtyUnitAbbr":"N/A","altQty":0.0,"isAltQtyEstimated":false,"netWgt":805860.172,"isNetWgtEstimated":true,"grossWgt":0.0,"isGrossWgtEstimated":false,"cifvalue":4336897.0,"fobvalue":null,"primaryValue":4336897.0,"legacyEstimationFlag":6,"isReported":false,"isAggregate":true},{"typeCode":"C","freqCode":"A","refPeriodId":20230101,"refYear":2023,"refMonth":52,"period":"2023","reporterCode":156,"reporterISO":"CHN","reporterDesc":"China","flowCode":"M","flowDesc":"Import","partnerCode":702,"partnerISO":"SGP","partnerDesc":"Singapore","partner2Code":0,"partner2ISO":"W00","partner2Desc":"World","classificationCode":"H6","classificationSearchCode":"HS","isOriginalClassification":true,"cmdCode":"2846","cmdDesc":"Compounds, inorganic or organic, of rare-earth metals; of yttrium or of scandium or of mixtures of these metals","aggrLevel":4,"isLeaf":false,"customsCode":"C00","customsDesc":"TOTAL CPC","mosCode":"0","motCode":0,"motDesc":"TOTAL MOT","qtyUnitCode":8,"qtyUnitAbbr":"kg","qty":196.825,"isQtyEstimated":true,"altQtyUnitCode":-1,"altQtyUnitAbbr":"N/A","altQty":0.0,"isAltQtyEstimated":false,"netWgt":196.825,"isNetWgtEstimated":true,"grossWgt":0.0,"isGrossWgtEstimated":false,"cifvalue":581.0,"fobvalue":null,"primaryValue":581.0,"legacyEstimationFlag":6,"isReported":false,"isAggregate":true},{"typeCode":"C","freqCode":"A","refPeriodId":20230101,"refYear":2023,"refMonth":52,"period":"2023","reporterCode":156,"reporterISO":"CHN","reporterDesc":"China","flowCode":"M","flowDesc":"Import","partnerCode":704,"partnerISO":"VNM","partnerDesc":"Viet Nam","partner2Code":0,"partner2ISO":"W00","partner2Desc":"World","classificationCode":"H6","classificationSearchCode":"HS","isOriginalClassification":true,"cmdCode":"2846","cmdDesc":"Compounds, inorganic or organic, of rare-earth metals; of yttrium or of scandium or of mixtures of these metals","aggrLevel":4,"isLeaf":false,"customsCode":"C00","customsDesc":"TOTAL CPC","mosCode":"0","motCode":0,"motDesc":"TOTAL MOT","qtyUnitCode":8,"qtyUnitAbbr":"kg","qty":3205314.0,"isQtyEstimated":false,"altQtyUnitCode":8,"altQtyUnitAbbr":"kg","altQty":3205314.0,"isAltQtyEstimated":false,"netWgt":3205314.0,"isNetWgtEstimated":false,"grossWgt":0.0,"isGrossWgtEstimated":false,"cifvalue":45875578.0,"fobvalue":null,"primaryValue":45875578.0,"legacyEstimationFlag":0,"isReported":false,"isAggregate":true},{"typeCode":"C","freqCode":"A","refPeriodId":20230101,"refYear":2023,"refMonth":52,"period":"2023","reporterCode":156,"reporterISO":"CHN","reporterDesc":"China","flowCode":"M","flowDesc":"Import","partnerCode":710,"partnerISO":"ZAF","partnerDesc":"South Africa","partner2Code":0,"partner2ISO":"W00","partner2Desc":"World","classificationCode":"H6","classificationSearchCode":"HS","isOriginalClassification":true,"cmdCode":"2846","cmdDesc":"Compounds, inorganic or organic, of rare-earth metals; of yttrium or of scandium or of mixtures of these metals","aggrLevel":4,"isLeaf":false,"customsCode":"C00","customsDesc":"TOTAL CPC","mosCode":"0","motCode":0,"motDesc":"TOTAL MOT","qtyUnitCode":8,"qtyUnitAbbr":"kg","qty":20000.0,"isQtyEstimated":false,"altQtyUnitCode":8,"altQtyUnitAbbr":"kg","altQty":20000.0,"isAltQtyEstimated":false,"netWgt":20000.0,"isNetWgtEstimated":false,"grossWgt":0.0,"isGrossWgtEstimated":false,"cifvalue":439000.0,"fobvalue":null,"primaryValue":439000.0,"legacyEstimationFlag":0,"isReported":false,"isAggregate":true},{"typeCode":"C","freqCode":"A","refPeriodId":20230101,"refYear":2023,"refMonth":52,"period":"2023","reporterCode":156,"reporterISO":"CHN","reporterDesc":"China","flowCode":"M","flowDesc":"Import","partnerCode":757,"partnerISO":"CHE","partnerDesc":"Switzerland","partner2Code":0,"partner2ISO":"W00","partner2Desc":"World","classificationCode":"H6","classificationSearchCode":"HS","isOriginalClassification":true,"cmdCode":"2846","cmdDesc":"Compounds, inorganic or organic, of rare-earth metals; of yttrium or of scandium or of mixtures of these metals","aggrLevel":4,"isLeaf":false,"customsCode":"C00","customsDesc":"TOTAL CPC","mosCode":"0","motCode":0,"motDesc":"TOTAL MOT","qtyUnitCode":8,"qtyUnitAbbr":"kg","qty":4131.277,"isQtyEstimated":true,"altQtyUnitCode":-1,"altQtyUnitAbbr":"N/A","altQty":0.0,"isAltQtyEstimated":false,"netWgt":4131.277,"isNetWgtEstimated":true,"grossWgt":0.0,"isGrossWgtEstimated":false,"cifvalue":280291.0,"fobvalue":null,"primaryValue":280291.0,"legacyEstimationFlag":6,"isReported":false,"isAggregate":true},{"typeCode":"C","freqCode":"A","refPeriodId":20230101,"refYear":2023,"refMonth":52,"period":"2023","reporterCode":156,"reporterISO":"CHN","reporterDesc":"China","flowCode":"M","flowDesc":"Import","partnerCode":764,"partnerISO":"THA","partnerDesc":"Thailand","partner2Code":0,"partner2ISO":"W00","partner2Desc":"World","classificationCode":"H6","classificationSearchCode":"HS","isOriginalClassification":true,"cmdCode":"2846","cmdDesc":"Compounds, inorganic or organic, of rare-earth metals; of yttrium or of scandium or of mixtures of these metals","aggrLevel":4,"isLeaf":false,"customsCode":"C00","customsDesc":"TOTAL CPC","mosCode":"0","motCode":0,"motDesc":"TOTAL MOT","qtyUnitCode":8,"qtyUnitAbbr":"kg","qty":38800.0,"isQtyEstimated":false,"altQtyUnitCode":8,"altQtyUnitAbbr":"kg","altQty":38800.0,"isAltQtyEstimated":false,"netWgt":38800.0,"isNetWgtEstimated":false,"grossWgt":0.0,"isGrossWgtEstimated":false,"cifvalue":1420459.0,"fobvalue":null,"primaryValue":1420459.0,"legacyEstimationFlag":0,"isReported":false,"isAggregate":true},{"typeCode":"C","freqCode":"A","refPeriodId":20230101,"refYear":2023,"refMonth":52,"period":"2023","reporterCode":156,"reporterISO":"CHN","reporterDesc":"China","flowCode":"M","flowDesc":"Import","partnerCode":792,"partnerISO":"TUR","partnerDesc":"Türkiye","partner2Code":0,"partner2ISO":"W00","partner2Desc":"World","classificationCode":"H6","classificationSearchCode":"HS","isOriginalClassification":true,"cmdCode":"2846","cmdDesc":"Compounds, inorganic or organic, of rare-earth metals; of yttrium or of scandium or of mixtures of these metals","aggrLevel":4,"isLeaf":false,"customsCode":"C00","customsDesc":"TOTAL CPC","mosCode":"0","motCode":0,"motDesc":"TOTAL MOT","qtyUnitCode":8,"qtyUnitAbbr":"kg","qty":251.706,"isQtyEstimated":true,"altQtyUnitCode":-1,"altQtyUnitAbbr":"N/A","altQty":0.0,"isAltQtyEstimated":false,"netWgt":251.706,"isNetWgtEstimated":true,"grossWgt":0.0,"isGrossWgtEstimated":false,"cifvalue":6387.0,"fobvalue":null,"primaryValue":6387.0,"legacyEstimationFlag":6,"isReported":false,"isAggregate":true},{"typeCode":"C","freqCode":"A","refPeriodId":20230101,"refYear":2023,"refMonth":52,"period":"2023","reporterCode":156,"reporterISO":"CHN","reporterDesc":"China","flowCode":"M","flowDesc":"Import","partnerCode":804,"partnerISO":"UKR","partnerDesc":"Ukraine","partner2Code":0,"partner2ISO":"W00","partner2Desc":"World","classificationCode":"H6","classificationSearchCode":"HS","isOriginalClassification":true,"cmdCode":"2846","cmdDesc":"Compounds, inorganic or organic, of rare-earth metals; of yttrium or of scandium or of mixtures of these metals","aggrLevel":4,"isLeaf":false,"customsCode":"C00","customsDesc":"TOTAL CPC","mosCode":"0","motCode":0,"motDesc":"TOTAL MOT","qtyUnitCode":8,"qtyUnitAbbr":"kg","qty":15.223,"isQtyEstimated":true,"altQtyUnitCode":-1,"altQtyUnitAbbr":"N/A","altQty":0.0,"isAltQtyEstimated":false,"netWgt":15.223,"isNetWgtEstimated":true,"grossWgt":0.0,"isGrossWgtEstimated":false,"cifvalue":268.0,"fobvalue":null,"primaryValue":268.0,"legacyEstimationFlag":6,"isReported":false,"isAggregate":true},{"typeCode":"C","freqCode":"A","refPeriodId":20230101,"refYear":2023,"refMonth":52,"period":"2023","reporterCode":156,"reporterISO":"CHN","reporterDesc":"China","flowCode":"M","flowDesc":"Import","partnerCode":826,"partnerISO":"GBR","partnerDesc":"United Kingdom","partner2Code":0,"partner2ISO":"W00","partner2Desc":"World","classificationCode":"H6","classificationSearchCode":"HS","isOriginalClassification":true,"cmdCode":"2846","cmdDesc":"Compounds, inorganic or organic, of rare-earth metals; of yttrium or of scandium or of mixtures of these metals","aggrLevel":4,"isLeaf":false,"customsCode":"C00","customsDesc":"TOTAL CPC","mosCode":"0","motCode":0,"motDesc":"TOTAL MOT","qtyUnitCode":8,"qtyUnitAbbr":"kg","qty":21193.822,"isQtyEstimated":true,"altQtyUnitCode":-1,"altQtyUnitAbbr":"N/A","altQty":0.0,"isAltQtyEstimated":false,"netWgt":21193.822,"isNetWgtEstimated":true,"grossWgt":0.0,"isGrossWgtEstimated":false,"cifvalue":640536.0,"fobvalue":null,"primaryValue":640536.0,"legacyEstimationFlag":6,"isReported":false,"isAggregate":true},{"typeCode":"C","freqCode":"A","refPeriodId":20230101,"refYear":2023,"refMonth":52,"period":"2023","reporterCode":156,"reporterISO":"CHN","reporterDesc":"China","flowCode":"M","flowDesc":"Import","partnerCode":842,"partnerISO":"USA","partnerDesc":"USA","partner2Code":0,"partner2ISO":"W00","partner2Desc":"World","classificationCode":"H6","classificationSearchCode":"HS","isOriginalClassification":true,"cmdCode":"2846","cmdDesc":"Compounds, inorganic or organic, of rare-earth metals; of yttrium or of scandium or of mixtures of these metals","aggrLevel":4,"isLeaf":false,"customsCode":"C00","customsDesc":"TOTAL CPC","mosCode":"0","motCode":0,"motDesc":"TOTAL MOT","qtyUnitCode":8,"qtyUnitAbbr":"kg","qty":503646.443,"isQtyEstimated":true,"altQtyUnitCode":-1,"altQtyUnitAbbr":"N/A","altQty":0.0,"isAltQtyEstimated":false,"netWgt":503646.443,"isNetWgtEstimated":true,"grossWgt":0.0,"isGrossWgtEstimated":false,"cifvalue":8718934.0,"fobvalue":null,"primaryValue":8718934.0,"legacyEstimationFlag":6,"isReported":false,"isAggregate":true},{"typeCode":"C","freqCode":"A","refPeriodId":20230101,"refYear":2023,"refMonth":52,"period":"2023","reporterCode":156,"reporterISO":"CHN","reporterDesc":"China","flowCode":"M","flowDesc":"Import","partnerCode":899,"partnerISO":"_X ","partnerDesc":"Areas, nes","partner2Code":0,"partner2ISO":"W00","partner2Desc":"World","classificationCode":"H6","classificationSearchCode":"HS","isOriginalClassification":true,"cmdCode":"2846","cmdDesc":"Compounds, inorganic or organic, of rare-earth metals; of yttrium or of scandium or of mixtures of these metals","aggrLevel":4,"isLeaf":false,"customsCode":"C00","customsDesc":"TOTAL CPC","mosCode":"0","motCode":0,"motDesc":"TOTAL MOT","qtyUnitCode":8,"qtyUnitAbbr":"kg","qty":4.885,"isQtyEstimated":true,"altQtyUnitCode":-1,"altQtyUnitAbbr":"N/A","altQty":0.0,"isAltQtyEstimated":false,"netWgt":4.885,"isNetWgtEstimated":true,"grossWgt":0.0,"isGrossWgtEstimated":false,"cifvalue":86.0,"fobvalue":null,"primaryValue":86.0,"legacyEstimationFlag":6,"isReported":false,"isAggregate":true}],"error":""}